kivy_animated_clock_package/__init__.py
kivy_animated_clock_package/clock.kv
kivy_animated_clock_package/main.py
kivy_animated_clock_package-1.0.dist-info/LICENSE
kivy_animated_clock_package-1.0.dist-info/METADATA
kivy_animated_clock_package-1.0.dist-info/WHEEL
kivy_animated_clock_package-1.0.dist-info/entry_points.txt
kivy_animated_clock_package-1.0.dist-info/top_level.txt
kivy_animated_clock_package-1.0.dist-info/RECORD
