Metadata-Version: 2.1
Name: kivy-animated-clock-package
Version: 1.0
Summary: Useful clock/stopwatch/timer written in Kivy
Home-page: UNKNOWN
Author: Daniel Kříž
License: MIT
Platform: UNKNOWN
Requires-Python: >=3.6
License-File: LICENSE
Requires-Dist: kivy
